{
	"configurations" : 
	[
		{
			"directories" : 
			[
				{
					"build" : ".",
					"hasInstallRule" : true,
					"jsonFile" : "directory-.-Release-161e9ea83cfd9f16dd50.json",
					"minimumCMakeVersion" : 
					{
						"string" : "3.1"
					},
					"projectIndex" : 0,
					"source" : ".",
					"targetIndexes" : 
					[
						0,
						1,
						2
					]
				}
			],
			"name" : "Release",
			"projects" : 
			[
				{
					"directoryIndexes" : 
					[
						0
					],
					"name" : "libuvc",
					"targetIndexes" : 
					[
						0,
						1,
						2
					]
				}
			],
			"targets" : 
			[
				{
					"directoryIndex" : 0,
					"id" : "example::@6890427a1f51a3e7e1df",
					"jsonFile" : "target-example-Release-d640f487eb28565f6f82.json",
					"name" : "example",
					"projectIndex" : 0
				},
				{
					"directoryIndex" : 0,
					"id" : "uvc::@6890427a1f51a3e7e1df",
					"jsonFile" : "target-uvc-Release-6760934f4f0c2d22bdbe.json",
					"name" : "uvc",
					"projectIndex" : 0
				},
				{
					"directoryIndex" : 0,
					"id" : "uvc_static::@6890427a1f51a3e7e1df",
					"jsonFile" : "target-uvc_static-Release-26e1f05242ab6e35f535.json",
					"name" : "uvc_static",
					"projectIndex" : 0
				}
			]
		}
	],
	"kind" : "codemodel",
	"paths" : 
	{
		"build" : "/home/gerardo/Projects/Robotics/RescueRobot2025/jaguar_odom/build/libuvc",
		"source" : "/home/gerardo/Projects/Robotics/RescueRobot2025/jaguar_odom/src/libuvc"
	},
	"version" : 
	{
		"major" : 2,
		"minor" : 3
	}
}
